{
    "configurations": [
        {
            "name": "Linux",
            "includePath": [
                "/usr/include",
                "/usr/local/include",
                "/usr/include/c++",
                "/usr/include/c++/5",
                "${workspaceRoot}",
                "/usr/include/x86_64-linux-gnu/c++/5",
                "/usr/include/linux"
            ],
            "defines": [],
            "intelliSenseMode": "clang-x64",
            "browse": {
                "path": [
                    "/usr/include",
                    "/usr/local/include",
                    "${workspaceRoot}"
                ],
                "limitSymbolsToIncludedHeaders": true,
                "databaseFilename": ""
            }
        }
    ],
    "version": 3
}